power_security_lib/__init__.py
power_security_lib/analyzer.py
power_security_lib/runner.py
power_security_lib-0.1.0.dist-info/LICENSE
power_security_lib-0.1.0.dist-info/METADATA
power_security_lib-0.1.0.dist-info/WHEEL
power_security_lib-0.1.0.dist-info/top_level.txt
power_security_lib-0.1.0.dist-info/RECORD
